MegEngine-1.13.1.data/data/megengine/ACKNOWLEDGMENTS
MegEngine-1.13.1.data/data/megengine/LICENSE
MegEngine-1.13.1.data/scripts/mge
megengine/__init__.py
megengine/_env_initlization.py
megengine/_multistream.py
megengine/config.py
megengine/conftest.py
megengine/device.py
megengine/logger.py
megengine/serialization.py
megengine/tensor.py
megengine/version.py
megengine/amp/__init__.py
megengine/amp/autocast.py
megengine/amp/convert_format.py
megengine/amp/grad_scaler.py
megengine/autodiff/__init__.py
megengine/autodiff/grad_manager.py
megengine/core/__init__.py
megengine/core/_config.py
megengine/core/_imperative_rt.cpython-36m-darwin.so
megengine/core/_trace_option.py
megengine/core/_wrap.py
megengine/core/autodiff/__init__.py
megengine/core/autodiff/grad.py
megengine/core/include/include/megbrain/custom/accessor.h
megengine/core/include/include/megbrain/custom/custom.h
megengine/core/include/include/megbrain/custom/data_adaptor.h
megengine/core/include/include/megbrain/custom/manager.h
megengine/core/include/include/megbrain/custom/op.h
megengine/core/include/include/megbrain/custom/param.h
megengine/core/include/include/megbrain/custom/param_val.h
megengine/core/include/include/megbrain/custom/tensor.h
megengine/core/include/include/megbrain/custom/utils.h
megengine/core/include/include/megbrain/custom/platform/custom_cuda.h
megengine/core/include/megbrain/custom/accessor.h
megengine/core/include/megbrain/custom/custom.h
megengine/core/include/megbrain/custom/data_adaptor.h
megengine/core/include/megbrain/custom/manager.h
megengine/core/include/megbrain/custom/op.h
megengine/core/include/megbrain/custom/param.h
megengine/core/include/megbrain/custom/param_val.h
megengine/core/include/megbrain/custom/tensor.h
megengine/core/include/megbrain/custom/utils.h
megengine/core/include/megbrain/custom/platform/custom_cuda.h
megengine/core/lib/libmegengine_shared.dylib
megengine/core/ops/__init__.py
megengine/core/ops/custom.py
megengine/core/ops/builtin/__init__.py
MegEngine-1.13.1.dist-info/METADATA
MegEngine-1.13.1.dist-info/WHEEL
MegEngine-1.13.1.dist-info/top_level.txt
MegEngine-1.13.1.dist-info/RECORD
